clickstock/__init__.py
clickstock/__main__.py
clickstock/operation.py
clickstock-1.0.1.dist-info/METADATA
clickstock-1.0.1.dist-info/WHEEL
clickstock-1.0.1.dist-info/entry_points.txt
clickstock-1.0.1.dist-info/top_level.txt
clickstock-1.0.1.dist-info/RECORD
