Metadata-Version: 2.1
Name: clickstock
Version: 1.0.1
Summary: I am clickstock
Home-page: https://github.com/MathieuCesbron?tab=repositories
Author: Mathieu Cesbron
Author-email: mathieuces@gmail.com
License: UNKNOWN
Platform: UNKNOWN
